{
  "default": {
    "mileage": [
      {
        "expression": "<%= mileage <= 3 %>",
        "price": 125,
        "modifier": false
      },
      {
        "expression": "<%= mileage > 3 && mileage <= 5 %>",
        "price": 165,
        "modifier": false
      },
      {
        "expression": "<%= !isNaN(rate) && rate > 0 %>",
        "price": "<%= mileage * rate %>",
        "modifier": false
      },
      {
        "expression": "<%= mileage > 5 && mileage < 10 %>",
        "price": "<%= mileage * 31 %>",
        "modifier": false
      },
      {
        "expression": "<%= mileage >= 10 && mileage < 20 %>",
        "price": "<%= mileage * 26 %>",
        "modifier": false
      }
    ],
    "mileageFinally": {
      "price": "<%= mileage * 24 %>",
      "modifier": false
    },
    "additionals": {
      "entries": 5,
      "entriesDiscount": 10,
      "buyin": 35,
      "buyout": 35,
      "takeIn": 35,
      "takeOut": 35,
      "bus": 75,
      "bundle": 5,
      "extraPoint": 20
    },
    "carMarkup": 0,
    "quickMarkup": 0
  },
  "Краснодар": {
    "mileage": [
      {
        "expression": "<%= mileage <= 3 %>",
        "price": 125,
        "modifier": false
      },
      {
        "expression": "<%= mileage > 3 && mileage <= 5 %>",
        "price": 165,
        "modifier": false
      },
      {
        "expression": "<%= !isNaN(rate) && rate > 0 %>",
        "price": "<%= mileage * rate %>",
        "modifier": false
      },
      {
        "expression": "<%= mileage > 5 && mileage < 10 %>",
        "price": "<%= mileage * 31 %>",
        "modifier": false
      },
      {
        "expression": "<%= mileage >= 10 && mileage < 20 %>",
        "price": "<%= mileage * 26 %>",
        "modifier": false
      }
    ],
    "mileageFinally": {
      "price": "<%= mileage * 24 %>",
      "modifier": false
    },
    "additionals": {
      "entries": 5,
      "entriesDiscount": 10,
      "buyin": 35,
      "buyout": 35,
      "takeIn": 35,
      "takeOut": 35,
      "bus": 75,
      "bundle": 5,
      "extraPoint": 20
    },
    "carMarkup": 0,
    "quickMarkup": 0
  },
  "Севастополь": {
    "mileage": [
      {
        "expression": "<%= mileage <= 3 %>",
        "price": 125,
        "modifier": false
      },
      {
        "expression": "<%= mileage > 3 && mileage <= 5 %>",
        "price": 165,
        "modifier": false
      },
      {
        "expression": "<%= !isNaN(rate) && rate > 0 %>",
        "price": "<%= mileage * rate %>",
        "modifier": false
      },
      {
        "expression": "<%= mileage > 5 && mileage < 10 %>",
        "price": "<%= mileage * 31 %>",
        "modifier": false
      },
      {
        "expression": "<%= mileage >= 10 && mileage < 20 %>",
        "price": "<%= mileage * 26 %>",
        "modifier": false
      }
    ],
    "mileageFinally": {
      "price": "<%= mileage * 24 %>",
      "modifier": false
    },
    "additionals": {
      "entries": 5,
      "entriesDiscount": 10,
      "buyin": 35,
      "buyout": 35,
      "takeIn": 35,
      "takeOut": 35,
      "bus": 75,
      "bundle": 5,
      "extraPoint": 20
    },
    "carMarkup": 0,
    "quickMarkup": 0
  },
  "Санкт-Петербург": {
    "mileage": [
      {
        "expression": "<%= mileage <= 3 %>",
        "price": 125,
        "modifier": false
      },
      {
        "expression": "<%= mileage > 3 && mileage <= 5 %>",
        "price": 165,
        "modifier": false
      },
      {
        "expression": "<%= !isNaN(rate) && rate > 0 %>",
        "price": "<%= mileage * rate %>",
        "modifier": false
      },
      {
        "expression": "<%= mileage > 5 && mileage < 10 %>",
        "price": "<%= mileage * 31 %>",
        "modifier": false
      },
      {
        "expression": "<%= mileage >= 10 && mileage < 20 %>",
        "price": "<%= mileage * 26 %>",
        "modifier": false
      }
    ],
    "mileageFinally": {
      "price": "<%= mileage * 24 %>",
      "modifier": false
    },
    "additionals": {
      "entries": 5,
      "entriesDiscount": 10,
      "buyin": 35,
      "buyout": 35,
      "takeIn": 35,
      "takeOut": 35,
      "bus": 75,
      "bundle": 5,
      "extraPoint": 20
    },
    "carMarkup": 0,
    "quickMarkup": 0
  },
  "Ставрополь": {
    "mileage": [
      {
        "expression": "<%= mileage <= 3 %>",
        "price": 125,
        "modifier": false
      },
      {
        "expression": "<%= mileage > 3 && mileage <= 5 %>",
        "price": 165,
        "modifier": false
      },
      {
        "expression": "<%= !isNaN(rate) && rate > 0 %>",
        "price": "<%= mileage * rate %>",
        "modifier": false
      },
      {
        "expression": "<%= mileage > 5 && mileage < 10 %>",
        "price": "<%= mileage * 31 %>",
        "modifier": false
      },
      {
        "expression": "<%= mileage >= 10 && mileage < 20 %>",
        "price": "<%= mileage * 26 %>",
        "modifier": false
      }
    ],
    "mileageFinally": {
      "price": "<%= mileage * 24 %>",
      "modifier": false
    },
    "additionals": {
      "entries": 5,
      "entriesDiscount": 10,
      "buyin": 35,
      "buyout": 35,
      "takeIn": 35,
      "takeOut": 35,
      "bus": 75,
      "bundle": 5,
      "extraPoint": 20
    },
    "carMarkup": 0,
    "quickMarkup": 0
  },
  "Симферополь": {
    "mileage": [
      {
        "expression": "<%= mileage <= 3 %>",
        "price": 125,
        "modifier": false
      },
      {
        "expression": "<%= mileage > 3 && mileage <= 5 %>",
        "price": 165,
        "modifier": false
      },
      {
        "expression": "<%= !isNaN(rate) && rate > 0 %>",
        "price": "<%= mileage * rate %>",
        "modifier": false
      },
      {
        "expression": "<%= mileage > 5 && mileage < 10 %>",
        "price": "<%= mileage * 31 %>",
        "modifier": false
      },
      {
        "expression": "<%= mileage >= 10 && mileage < 20 %>",
        "price": "<%= mileage * 26 %>",
        "modifier": false
      }
    ],
    "mileageFinally": {
      "price": "<%= mileage * 24 %>",
      "modifier": false
    },
    "additionals": {
      "entries": 5,
      "entriesDiscount": 10,
      "buyin": 35,
      "buyout": 35,
      "takeIn": 35,
      "takeOut": 35,
      "bus": 75,
      "bundle": 5,
      "extraPoint": 20
    },
    "carMarkup": 0,
    "quickMarkup": 0
  }
}
